Metadata-Version: 1.1
Name: ondevice
Version: 0.3
Summary: Client for the ondevice.io service
Home-page: https://github.com/ondevice/ondevice-client
Author: Manuel Reithuber
Author-email: info@ondevice.io
License: MIT
Keywords: remote ssh websockets cloud
Platform: UNKNOWN
Classifier: Development Status :: 3 - Alpha
Classifier: Intended Audience :: Developers
Classifier: Topic :: Software Development :: Build Tools
Classifier: License :: OSI Approved :: MIT License
Classifier: Programming Language :: Python :: 3
Classifier: Programming Language :: Python :: 3.2
Classifier: Programming Language :: Python :: 3.3
Classifier: Programming Language :: Python :: 3.4
Classifier: Programming Language :: Python :: 3.5
